rSpringRank/__init__.py
rSpringRank/datasets/__init__.py
rSpringRank/datasets/_fetchers.py
rSpringRank/datasets/_registry.py
rSpringRank/datasets/tests/__init__.py
rSpringRank/datasets/tests/test_phd_exchange.py
rSpringRank/datasets/tests/test_vanilla_springrank.py
rSpringRank/draw/__init__.py
rSpringRank/draw/utils.py
rSpringRank/io/__init__.py
rSpringRank/io/graph2mat.py
rSpringRank/io/tests/__init__.py
rSpringRank/io/utils.py
rSpringRank/optimize/__init__.py
rSpringRank/optimize/cvx.py
rSpringRank/optimize/firstOrderMethods.py
rSpringRank/optimize/losses.py
rSpringRank/optimize/models.py
rSpringRank/optimize/regularizers.py
rSpringRank/optimize/tests/__init__.py
rSpringRank/stats/__init__.py
rSpringRank/stats/cross_validation.py
rSpringRank/stats/experiments.py
rSpringRank/stats/tests/__init__.py
rspringrank-0.2.28.dist-info/LICENSE
rspringrank-0.2.28.dist-info/METADATA
rspringrank-0.2.28.dist-info/WHEEL
rspringrank-0.2.28.dist-info/RECORD
